[
    {
      "name": "Gandalf on Gwaihir",
      "description": "Gandalf on Gwaihir",
      "id": 1,
      "number": 1,
      "image": "/pops/Gandalf_Gwaihir.webp",
      "category": "El Señor de los Anillos",
      "price": 2750
    },
    {
      "name": "Gandalf",
      "description": "Gandalf",
      "id": 2,
      "number": 2,
      "image": "/pops/Gandalf.webp",
      "category": "El Señor de los Anillos",
      "price": 2600
    },
    {
      "name": "Frodo Baggins",
      "description": "Frodo Baggins",
      "id": 3,
      "number": 3,
      "image": "/pops/Frodo.webp",
      "category": "El Señor de los Anillos",
      "price": 2600
    },
    {
      "name": "Frodo Baggins (Glow Chase)",
      "description": "Frodo Baggins (Glow Chase) Limited Edition",
      "id": 4,
      "number": 4,
      "image": "/pops/Frodo_GlowChase.webp",
      "category": "El Señor de los Anillos",
      "price": 2700
    },
    {
      "name": "Samwise Gamgee",
      "description": "Samwise Gamgee",
      "id": 5,
      "number": 5,
      "image": "/pops/SamwiseGamgee.webp",
      "category": "El Señor de los Anillos",
      "price": 2600
    },
    {
      "name": "Nazgul",
      "description": "Nazgul",
      "id": 6,
      "number": 6,
      "image": "/pops/Nazgul.webp",
      "category": "El Señor de los Anillos",
      "price": 2600
    },
    {
      "name": "Balrog",
      "description": "Balrog",
      "id": 7,
      "number": 7,
      "image": "/pops/Balrog.webp",
      "category": "El Señor de los Anillos",
      "price": 2600
    },
    {
      "name": "Pippin Took",
      "description": "Pippin Took",
      "id": 8,
      "number": 8,
      "image": "/pops/PippinTook.webp",
      "category": "El Señor de los Anillos",
      "price": 2600
    },
    {
      "name": "Treebeard",
      "description": "Treebeard",
      "id": 9,
      "number": 9,
      "image": "/pops/TreeBeard.webp",
      "category": "El Señor de los Anillos",
      "price": 2600
    },
    {
      "name": "Aragorn",
      "description": "Aragorn",
      "id": 10,
      "number": 10,
      "image": "/pops/Aragorn.webp",
      "category": "El Señor de los Anillos",
      "price": 2700
    },
    {
      "name": "Gollum",
      "description": "Gollum",
      "id": 11,
      "number": 11,
      "image": "/pops/Gollum.webp",
      "category": "El Señor de los Anillos",
      "price": 2900
    },
    {
      "name": "Boromir",
      "description": "Boromir",
      "id": 12,
      "number": 12,
      "image": "/pops/Boromir.webp",
      "category": "El Señor de los Anillos",
      "price": 2600
    },
    {
      "name": "Galadriel",
      "description": "Galadriel",
      "id": 13,
      "number": 13,
      "image": "/pops/Galadriel.webp",
      "category": "El Señor de los Anillos",
      "price": 2600
    },
    {
      "name": "Dunharrow King",
      "description": "Dunharrow King",
      "id": 14,
      "number": 14,
      "image": "/pops/DunharrowKing.webp",
      "category": "El Señor de los Anillos",
      "price": 2600
    },
    {
      "name": "Galadriel (Tempted)",
      "description": "Galadriel (Tempted)",
      "id": 15,
      "number": 15,
      "image": "/pops/Galadriel_Tempted.webp",
      "category": "El Señor de los Anillos",
      "price": 2600
    },
    {
      "name": "Gandalf the White",
      "description": "Gandalf the White",
      "id": 16,
      "number": 16,
      "image": "/pops/GandalfWhite.webp",
      "category": "El Señor de los Anillos",
      "price": 2600
    },
    {
      "name": "Farva",
      "description": "Trooper Rodney 'Rod' Farva",
      "id": 17,
      "number": 17,
      "image": "/pops/Farva.webp",
      "category": "Super Troopers",
      "price": 2600
    },
    {
      "name": "Mac",
      "description": "Trooper MacIntyre 'Mac' Womack",
      "id": 18,
      "number": 18,
      "image": "/pops/Mac.webp",
      "category": "Super Troopers",
      "price": 2600
    },
    {
      "name": "Ramathorn",
      "description": "Trooper Arcot 'Thorny' Ramathorn",
      "id": 19,
      "number": 19,
      "image": "/pops/Ramathorn.webp",
      "category": "Super Troopers",
      "price": 2600
    },
    {
      "name": "Rabbit",
      "description": "Rabbit",
      "id": 20,
      "number": 20,
      "image": "/pops/Rabbit.webp",
      "category": "Super Troopers",
      "price": 2600
    },
    {
      "name": "Foster",
      "description": "Foster",
      "id": 21,
      "number": 21,
      "image": "/pops/Foster.webp",
      "category": "Super Troopers",
      "price": 2600
    },
    {
      "name": "Dr. Peter Venkman (Special Edition)",
      "description": "Dr. Peter Venkman (Special Edition) with Tee",
      "id": 22,
      "number": 22,
      "image": "/pops/PeterVenkman.webp",
      "category": "GhostBusters",
      "price": 3000
    },
    {
      "name": "Dr. Raymond Stantz",
      "description": "Dr. Raymond Stantz",
      "id": 23,
      "number": 23,
      "image": "/pops/RaymondStantz.webp",
      "category": "GhostBusters",
      "price": 2600
    },
    {
      "name": "Dr. Egon Spengler",
      "description": "Dr. Egon Spengler",
      "id": 24,
      "number": 24,
      "image": "/pops/EgonSpengler.webp",
      "category": "GhostBusters",
      "price": 2600
    },
    {
      "name": "Winston Zeddemore",
      "description": "Winston Zeddemore",
      "id": 25,
      "number": 25,
      "image": "/pops/WinstonZeddemore.webp",
      "category": "GhostBusters",
      "price": 2600
    },
    {
      "name": "Sub-Zero",
      "description": "Sub-Zero",
      "id": 26,
      "number": 26,
      "image": "/pops/SubZero.webp",
      "category": "Mortal Kombat",
      "price": 2800
    },
    {
      "name": "Liu Kang",
      "description": "Liu Kang",
      "id": 27,
      "number": 27,
      "image": "/pops/Liu.webp",
      "category": "Mortal Kombat",
      "price": 2800
    },
    {
      "name": "Raiden",
      "description": "Raiden",
      "id": 28,
      "number": 28,
      "image": "/pops/Raiden.webp",
      "category": "Mortal Kombat",
      "price": 2850
    },
    {
      "name": "Scorpion",
      "description": "Scorpion",
      "id": 29,
      "number": 29,
      "image": "/pops/Scorpion.webp",
      "category": "Mortal Kombat",
      "price": 3100
    },
    {
      "name": "Kitana",
      "description": "Kitana",
      "id": 30,
      "number": 30,
      "image": "/pops/Kitana.webp",
      "category": "Mortal Kombat",
      "price": 2600
    },
    {
      "name": "Black Knight",
      "description": "Black Knight",
      "id": 31,
      "number": 31,
      "image": "/pops/BlackKnight.webp",
      "category": "Monty Pyton",
      "price": 2600
    },
    {
      "name": "Tim the Enchanter",
      "description": "Tim the Enchanter",
      "id": 32,
      "number": 32,
      "image": "/pops/Tim.webp",
      "category": "Monty Pyton",
      "price": 2600
    },
    {
      "name": "French Taunter",
      "description": "French Taunter",
      "id": 33,
      "number": 33,
      "image": "/pops/FrenchTaunter.webp",
      "category": "Monty Pyton",
      "price": 2600
    },
    {
      "name": "Black Knight (Missing Arms)",
      "description": "Black Knight (Missing Arms)",
      "id": 34,
      "number": 34,
      "image": "/pops/BlackKnightFLESHWOUND.webp",
      "category": "Monty Pyton",
      "price": 2600
    },
    {
      "name": "Dr. Emmett Brown",
      "description": "Dr. Emmett Brown",
      "id": 35,
      "number": 35,
      "image": "/pops/DocBrown.webp",
      "category": "Back to the Future",
      "price": 3000
    },
    {
      "name": "Marty McFly",
      "description": "Marty McFly",
      "id": 36,
      "number": 36,
      "image": "/pops/McFly.webp",
      "category": "Back to the Future",
      "price": 2950
    },
    {
      "name": "Jon Snow",
      "description": "Jon Snow",
      "id": 37,
      "number": 37,
      "image": "/pops/JonSnow.webp",
      "category": "Game of Thrones",
      "price": 2600
    },
    {
      "name": "Drogon",
      "description": "Drogon",
      "id": 38,
      "number": 38,
      "image": "/pops/Drogon.webp",
      "category": "Game of Thrones",
      "price": 2600
    },
    {
      "name": "Poison Ivy",
      "description": "Poison Ivy",
      "id": 39,
      "number": 39,
      "image": "/pops/PoisonIvy.webp",
      "category": "DC Comics Bombshells",
      "price": 2600
    },
    {
      "name": "Maleficent",
      "description": "Maleficent",
      "id": 40,
      "number": 40,
      "image": "/pops/Maleficent.webp",
      "category": "Disney",
      "price": 2600
    },
    {
      "name": "Rick Deckard",
      "description": "Rick Deckard",
      "id": 41,
      "number": 41,
      "image": "/pops/1032_BladeRunner_RickDeckard.webp",
      "category": "Blade Runner",
      "price": 2600
    },
    {
      "name": "Rachael",
      "description": "Rachael",
      "id": 42,
      "number": 42,
      "image": "/pops/1033_BladeRunner_Rachael.webp",
      "category": "Blade Runner",
      "price": 2600
    },
    {
      "name": "Roy Batty",
      "description": "Roy Batty",
      "id": 43,
      "number": 43,
      "image": "/pops/1034_BladeRunner_RoyBatty.webp",
      "category": "Blade Runner",
      "price": 2600
    },
    {
      "name": "Pris",
      "description": "Pris",
      "id": 44,
      "number": 44,
      "image": "/pops/1035_BladeRunner_Pris.webp",
      "category": "Blade Runner",
      "price": 2600
    },
    {
      "name": "Deckard",
      "description": "Deckard",
      "id": 45,
      "number": 45,
      "image": "/pops/Deckard.webp",
      "category": "Blade Runner 2049",
      "price": 2600
    },
    {
      "name": "Officer K",
      "description": "Officer K",
      "id": 46,
      "number": 46,
      "image": "/pops/OfficerK.webp",
      "category": "Blade Runner 2049",
      "price": 2600
    },
    {
      "name": "Wallace",
      "description": "Wallace",
      "id": 47,
      "number": 47,
      "image": "/pops/Wallace.webp",
      "category": "Blade Runner 2049",
      "price": 2600
    },
    {
      "name": "Sapper",
      "description": "Sapper",
      "id": 48,
      "number": 48,
      "image": "/pops/Sapper.webp",
      "category": "Blade Runner 2049",
      "price": 2600
    },
    {
      "name": "Bill Lumbergh",
      "description": "Bill Lumbergh",
      "id": 49,
      "number": 49,
      "image": "/pops/BillLumbergh.webp",
      "category": "OfficeSpace",
      "price": 2600
    },
    {
      "name": "Darth Vader",
      "description": "Darth Vader (Lidl Exclusive)",
      "id": 50,
      "number": 50,
      "image": "/pops/DarthVader.webp",
      "category": "Star Wars",
      "price": 3200
    },
    {
      "name": "Darth Vader",
      "description": "Darth Vader (Electrocuted)",
      "id": 51,
      "number": 51,
      "image": "/pops/DarthVaderElectrocuted.webp",
      "category": "Star Wars",
      "price": 3250
    },
    {
      "name": "Gambit",
      "description": "Gambit with Cards",
      "id": 52,
      "number": 52,
      "image": "/pops/Gambit.webp",
      "category": "X-Men",
      "price": 2600
    },
    {
      "name": "Gambit",
      "description": "Gambit with Bo Staff",
      "id": 53,
      "number": 53,
      "image": "/pops/gambit_staff.webp",
      "category": "X-Men",
      "price": 2600
    },
    {
      "name": "Neo",
      "description": "2021",
      "id": 54,
      "number": 54,
      "image": "/pops/Neo.webp",
      "category": "The Matrix",
      "price": 3000
    },
    {
      "name": "Morpheus",
      "description": "2021 (Only at Target)",
      "id": 55,
      "number": 55,
      "image": "/pops/Morpheus-1175.webp",
      "category": "The Matrix",
      "price": 2600
    },
    {
      "name": "The Analyst",
      "description": "2021 (Walmart Exclusive)",
      "id": 56,
      "number": 56,
      "image": "/pops/TheAnalyst-1176.webp",
      "category": "The Matrix",
      "price": 2600
    }
]
